basilico/__init__.py
basilico/alpine.py
basilico/attributes.py
basilico/components.py
basilico/elements.py
basilico/htmx.py
basilico/node.py
basilico/py.typed
basilico-0.1.0.dist-info/METADATA
basilico-0.1.0.dist-info/WHEEL
basilico-0.1.0.dist-info/licenses/LICENSE.md
basilico-0.1.0.dist-info/RECORD
